setup.py
disref/__init__.py
disref/cache.py
disref/update.py
disref.egg-info/PKG-INFO
disref.egg-info/SOURCES.txt
disref.egg-info/dependency_links.txt
disref.egg-info/requires.txt
disref.egg-info/top_level.txt