Metadata-Version: 1.1
Name: disref
Version: 0.1
Summary: Provides easy, fault tolerant, distributed references with redis as a backend.
Home-page: http://www.github.com/buzzfeed/disref
Author: Andrew Kelleher
Author-email: andrew.kelleher@buzzfeed.com
License: UNKNOWN
Keywords: distributed reference references aggregation pipeline big data online algorithm
Platform: UNKNOWN
Classifier: Intended Audience :: Developers
Classifier: Intended Audience :: System Administrators
